dicomindex/__init__.py
dicomindex/cli.py
dicomindex/core.py
dicomindex/dataset.py
dicomindex/exceptions.py
dicomindex/fields.py
dicomindex/iterators.py
dicomindex/logs.py
dicomindex/orm.py
dicomindex/persistence.py
dicomindex/processing.py
dicomindex/statistics.py
dicomindex/threading.py
dicomindex/types.py
dicomindex-0.3.0.dist-info/WHEEL
dicomindex-0.3.0.dist-info/entry_points.txt
dicomindex-0.3.0.dist-info/METADATA
dicomindex-0.3.0.dist-info/RECORD
