Metadata-Version: 2.4
Name: dicomindex
Version: 0.3.0
Summary: Index dicom files into sqlite database
Author: sjoerdk
Author-email: sjoerdk <sjoerd.kerkstra@radboudumc.nl>
License-Expression: MIT
Classifier: Programming Language :: Python :: 3.10
Classifier: Programming Language :: Python :: 3.11
Classifier: Programming Language :: Python :: 3.12
Classifier: Programming Language :: Python :: 3.13
Classifier: Programming Language :: Python :: 3.14
Requires-Dist: dicomgenerator>=0.9.0
Requires-Dist: pydicom>=2.4.4
Requires-Dist: sqlalchemy>=2.0.46
Requires-Dist: tabulate>=0.9.0
Requires-Dist: tqdm>=4.67.1
Requires-Python: >=3.10, <4
